reaper/.__init__.py.swp
reaper/.__init__.py.un~
reaper/__init__.py
reaper-0.0.1.dist-info/METADATA
reaper-0.0.1.dist-info/WHEEL
reaper-0.0.1.dist-info/RECORD
