Metadata-Version: 1.2
Name: reaper
Version: 0.0.1
Summary: Reaper
Home-page: https://github.com/Carreau/reaper
License: UNKNOWN
Author: Matthias Bussonnier
Author-email: bussonniermatthias@gmail.com
Classifier: License :: OSI Approved :: MIT License
Requires-Dist: semver
Requires-Dist: traitlets
